streamlit_authenticator/__init__.py
streamlit_authenticator/params.py
streamlit_authenticator/controllers/__init__.py
streamlit_authenticator/controllers/authentication_controller.py
streamlit_authenticator/controllers/cookie_controller.py
streamlit_authenticator/models/__init__.py
streamlit_authenticator/models/authentication_model.py
streamlit_authenticator/models/cookie_model.py
streamlit_authenticator/models/cloud/__init__.py
streamlit_authenticator/models/cloud/cloud_model.py
streamlit_authenticator/models/oauth2/__init__.py
streamlit_authenticator/models/oauth2/google_model.py
streamlit_authenticator/models/oauth2/microsoft_model.py
streamlit_authenticator/utilities/__init__.py
streamlit_authenticator/utilities/encryptor.py
streamlit_authenticator/utilities/exceptions.py
streamlit_authenticator/utilities/hasher.py
streamlit_authenticator/utilities/helpers.py
streamlit_authenticator/utilities/validator.py
streamlit_authenticator/views/__init__.py
streamlit_authenticator/views/authentication_view.py
streamlit_authenticator-0.4.3.dist-info/LICENSE
streamlit_authenticator-0.4.3.dist-info/METADATA
streamlit_authenticator-0.4.3.dist-info/WHEEL
streamlit_authenticator-0.4.3.dist-info/top_level.txt
streamlit_authenticator-0.4.3.dist-info/RECORD
