Metadata-Version: 2.1
Name: streamlit-authenticator
Version: 0.4.3
Summary: A secure authentication module to manage user access in a Streamlit application.
Home-page: https://github.com/mkhorasani/Streamlit-Authenticator
Author: Mohammad Khorasani
Author-email: khorasani.mohammad@gmail.com
Keywords: Python,Streamlit,Authentication,Components
Classifier: Programming Language :: Python :: 3
Classifier: License :: OSI Approved :: MIT License
Classifier: Operating System :: OS Independent
Requires-Python: >=3.6
License-File: LICENSE
Requires-Dist: bcrypt >=3.1.7
Requires-Dist: captcha >=0.5.0
Requires-Dist: cryptography >=42.0.5
Requires-Dist: PyJWT >=2.3.0
Requires-Dist: PyYAML >=5.3.1
Requires-Dist: streamlit >=1.37.0
Requires-Dist: streamlit-javascript >=0.1.5
